list_sponsors/__init__.py
list_sponsors/__main__.py
list_sponsors/__version__.py
list_sponsors/_const.py
list_sponsors/_gh_client.py
list_sponsors/_logger.py
list_sponsors/_sponsor.py
list_sponsors-0.1.0.dist-info/LICENSE
list_sponsors-0.1.0.dist-info/METADATA
list_sponsors-0.1.0.dist-info/WHEEL
list_sponsors-0.1.0.dist-info/entry_points.txt
list_sponsors-0.1.0.dist-info/top_level.txt
list_sponsors-0.1.0.dist-info/RECORD
