Metadata-Version: 2.1
Name: list-sponsors
Version: 0.1.0
Summary: A CLI tool to list GitHub sponsors of a user/organization with a specified format.
Home-page: https://github.com/thombashi/list-sponsors
Author: Tsuyoshi Hombashi
Author-email: tsuyoshi.hombashi@gmail.com
License: MIT License
Project-URL: Changelog, https://github.com/thombashi/list-sponsors/releases
Project-URL: Source, https://github.com/thombashi/list-sponsors
Project-URL: Tracker, https://github.com/thombashi/list-sponsors/issues
Keywords: GitHub,sponsors
Classifier: Development Status :: 4 - Beta
Classifier: Environment :: Console
Classifier: Intended Audience :: Information Technology
Classifier: License :: OSI Approved :: MIT License
Classifier: Operating System :: OS Independent
Classifier: Programming Language :: Python :: 3
Classifier: Programming Language :: Python :: 3.8
Classifier: Programming Language :: Python :: 3.9
Classifier: Programming Language :: Python :: 3.10
Classifier: Programming Language :: Python :: 3.11
Classifier: Programming Language :: Python :: 3.12
Classifier: Programming Language :: Python :: 3 :: Only
Classifier: Topic :: Terminals
Requires-Python: >=3.8
License-File: LICENSE
Requires-Dist: loguru <1,>=0.4.1
Requires-Dist: retryrequests <1,>=0.2.0
Provides-Extra: test
Requires-Dist: pytest ; extra == 'test'
